LICENSE
MANIFEST.in
README.md
setup.cfg
setup.py
carousels/__init__.py
carousels/admin.py
carousels/models.py
carousels/locale/sk/LC_MESSAGES/django.mo
carousels/locale/sk/LC_MESSAGES/django.po
carousels/migrations/0001_initial.py
carousels/migrations/0002_carousel_settings.py
carousels/migrations/__init__.py
carousels/templates/carousels/carousel.html
carousels/templatetags/__init__.py
carousels/templatetags/carousels.py
django_carousels.egg-info/PKG-INFO
django_carousels.egg-info/SOURCES.txt
django_carousels.egg-info/dependency_links.txt
django_carousels.egg-info/requires.txt
django_carousels.egg-info/top_level.txt