Metadata-Version: 1.2
Name: django-carousels
Version: 0.1.3
Summary: Django app for model-based carousels
Home-page: https://github.com/PragmaticMates/django-carousels
Author: Pragmatic Mates
Author-email: info@pragmaticmates.com
Maintainer: Pragmatic Mates
Maintainer-email: info@pragmaticmates.com
License: GNU General Public License (GPL)
Keywords: django UI carousel
Platform: UNKNOWN
Classifier: Programming Language :: Python
Classifier: Programming Language :: Python :: 3.9
Classifier: Operating System :: OS Independent
Classifier: Environment :: Web Environment
Classifier: Intended Audience :: Developers
Classifier: Framework :: Django
Classifier: License :: OSI Approved :: GNU General Public License (GPL)
Classifier: Development Status :: 3 - Alpha
